{
  "/_not-found/page": "app/_not-found/page.js",
  "/favicon.ico/route": "app/favicon.ico/route.js",
  "/[slug]/page": "app/[slug]/page.js",
  "/gallery/page": "app/gallery/page.js",
  "/news/[slug]/page": "app/news/[slug]/page.js",
  "/page": "app/page.js",
  "/case-studies/[slug]/page": "app/case-studies/[slug]/page.js",
  "/doctors-list/page": "app/doctors-list/page.js",
  "/case-studies/page": "app/case-studies/page.js",
  "/resources/page": "app/resources/page.js",
  "/resources/[slug]/page": "app/resources/[slug]/page.js",
  "/news/page": "app/news/page.js",
  "/testimonials/page": "app/testimonials/page.js",
  "/admin/case-study-categories/add/page": "app/admin/case-study-categories/add/page.js",
  "/admin/case-study-categories/page": "app/admin/case-study-categories/page.js",
  "/admin/case-study-type/add/page": "app/admin/case-study-type/add/page.js",
  "/admin/case-study-type/[id]/page": "app/admin/case-study-type/[id]/page.js",
  "/admin/case-study-categories/[id]/page": "app/admin/case-study-categories/[id]/page.js",
  "/admin/case-study/[id]/page": "app/admin/case-study/[id]/page.js",
  "/admin/case-study/page": "app/admin/case-study/page.js",
  "/admin/case-study/add/page": "app/admin/case-study/add/page.js",
  "/admin/contact-form/page": "app/admin/contact-form/page.js",
  "/admin/case-study-type/page": "app/admin/case-study-type/page.js",
  "/admin/doctors-list/[id]/page": "app/admin/doctors-list/[id]/page.js",
  "/admin/doctors-list/add/page": "app/admin/doctors-list/add/page.js",
  "/admin/gallery/[id]/page": "app/admin/gallery/[id]/page.js",
  "/admin/doctors-list/page": "app/admin/doctors-list/page.js",
  "/admin/gallery/add/page": "app/admin/gallery/add/page.js",
  "/admin/login/page": "app/admin/login/page.js",
  "/admin/gallery/page": "app/admin/gallery/page.js",
  "/admin/menus/[id]/page": "app/admin/menus/[id]/page.js",
  "/admin/menus/add/[type]/page": "app/admin/menus/add/[type]/page.js",
  "/admin/menus/page": "app/admin/menus/page.js",
  "/admin/news-categories/[id]/page": "app/admin/news-categories/[id]/page.js",
  "/admin/news-categories/add/page": "app/admin/news-categories/add/page.js",
  "/admin/news-categories/page": "app/admin/news-categories/page.js",
  "/admin/news/[id]/page": "app/admin/news/[id]/page.js",
  "/admin/news/add/page": "app/admin/news/add/page.js",
  "/admin/news/page": "app/admin/news/page.js",
  "/admin/pages/add/page": "app/admin/pages/add/page.js",
  "/admin/page": "app/admin/page.js",
  "/admin/pages/[id]/page": "app/admin/pages/[id]/page.js",
  "/admin/pages/page": "app/admin/pages/page.js",
  "/admin/profile/page": "app/admin/profile/page.js",
  "/admin/resources/add/page": "app/admin/resources/add/page.js",
  "/admin/resources/page": "app/admin/resources/page.js",
  "/admin/settings/page": "app/admin/settings/page.js",
  "/admin/resources/[id]/page": "app/admin/resources/[id]/page.js",
  "/admin/testimonial-categories/[id]/page": "app/admin/testimonial-categories/[id]/page.js",
  "/admin/testimonial-categories/add/page": "app/admin/testimonial-categories/add/page.js",
  "/admin/testimonial-categories/page": "app/admin/testimonial-categories/page.js",
  "/admin/testimonials/[id]/page": "app/admin/testimonials/[id]/page.js",
  "/admin/testimonials/add/page": "app/admin/testimonials/add/page.js",
  "/admin/testimonials/page": "app/admin/testimonials/page.js",
  "/admin/users/[id]/page": "app/admin/users/[id]/page.js",
  "/admin/users/add/page": "app/admin/users/add/page.js",
  "/admin/users/page": "app/admin/users/page.js"
}